exmlrd/__init__.py
exmlrd/archive.py
exmlrd/cell.py
exmlrd/excel.py
exmlrd/exceptions.py
exmlrd/log.py
exmlrd/sharedstyle.py
exmlrd/styles.py
exmlrd/tags.py
exmlrd/tools.py
exsample/convert_json.py
exsample/get_cell.py
exsample/get_mergecell.py
exsample/get_sheetname.py
venv/bin/rst2html.py
venv/bin/rst2html4.py
venv/bin/rst2html5.py
venv/bin/rst2latex.py
venv/bin/rst2man.py
venv/bin/rst2odt.py
venv/bin/rst2odt_prepstyles.py
venv/bin/rst2pseudoxml.py
venv/bin/rst2s5.py
venv/bin/rst2xetex.py
venv/bin/rst2xml.py
venv/bin/rstpep2html.py
exmlrd-1.0.4.dist-info/LICENCE
exmlrd-1.0.4.dist-info/METADATA
exmlrd-1.0.4.dist-info/WHEEL
exmlrd-1.0.4.dist-info/top_level.txt
exmlrd-1.0.4.dist-info/RECORD
