Metadata-Version: 2.1
Name: exmlrd
Version: 1.0.4
Summary: Python module for simple reading of Excel(.xlsx)
Author-email: Hayato Sonokawa <hsono10n1@gmail.com>
Project-URL: Homepage, https://github.com/sonoh5n/exml-reader
Project-URL: Bug Tracker, https://github.com/sonoh5n/exml-reader/issues
Classifier: Programming Language :: Python :: 3
Classifier: License :: OSI Approved :: MIT License
Classifier: Operating System :: OS Independent
Requires-Python: >=3.8
License-File: LICENCE
